Workbook

Sheet Sheet1
A1: Company | B1: Year | C1: Assets | D1: Liabilities | E1: Equity(F-G) | F1: Revenue | G1: Operating Expenses | H1: EBITDA | I1: Net Income | J1: EPS | K1: CF-Operations | L1: CF-Investing | M1: CF-Investing N | N1: Free Cash Flow(K-L) | O1: CF - Financing | P1: Free Cash Flow(K-L) | Q1: Stock Price | R1: P/E Ratio(O/J) | S1: Return on Assets(I/F) | T1: Reference Exchange | U1: Volatility(Beta) | V1: Sharpe Ratio
A2: ANTERO RESOURCES Corp | B2: 2013 | C2: 6613581 | D2: 3014921 | E2: =C2-D2 -> 3598660 | F2: 1313134 | G2: 971927 | H2: =F2-G2 -> 341207 | I2: -18930 | J2: -0.09 | K2: 534707 | L2: 2673592 | M2: -2673592 | N2: =K2+M2 -> -2138885 | O2: 2137383 | P2: =K2-L2 -> -2138885 | Q2: 63.15 | R2: =Q2/J2 -> -701.66667 | S2: =I2/C2 -> -0.002862292 | T2: NASDAQ
A3: ANTERO RESOURCES Corp | B3: 2014 | C3: 11573495 | D3: 6099665 | E3: =C3-D3 -> 5473830 | F3: 2720632 | G3: 1420898 | H3: =F3-G3 -> 1299734 | I3: 673587 | J3: 2.57 | K3: 998121 | L3: 4089650 | M3: -4089650 | N3: =K3+M3 -> -3091529 | O3: 3320021 | P3: =K3-L3 -> -3091529 | Q3: 40.6 | R3: =Q3/J3 -> 15.797665 | S3: =I3/C3 -> 0.058200829 | T3: NASDAQ
A4: ANTERO RESOURCES Corp | B4: 2015 | C4: 14155224 | D4: 6868546 | E4: =C4-D4 -> 7286678 | F4: 3954858 | G4: 2164572 | H4: =F4-G4 -> 1790286 | I4: 941364 | J4: 3.43 | K4: 1006381 | L4: 2298159 | M4: -2298159 | N4: =K4+M4 -> -1291778 | O4: 1069272 | P4: =K4-L4 -> -1291778 | Q4: 21.75 | R4: =Q4/J4 -> 6.3411079 | S4: =I4/C4 -> 0.066502939 | T4: NASDAQ
A5: ANTERO RESOURCES Corp | B5: 2016 | C5: 14255550 | D5: 6526972 | E5: =C5-D5 -> 7728578 | F5: 1744525 | G5: 2720326 | H5: =F5-G5 -> -975801 | I5: -848816 | J5: -2.88 | K5: 1241256 | L5: 2395138 | M5: -2395138 | N5: =K5+M5 -> -1153882 | O5: 1162019 | P5: =K5-L5 -> -1153882 | Q5: 23.89 | R5: =Q5/J5 -> -8.2951389 | S5: =I5/C5 -> -0.059542845 | T5: NASDAQ
A6: ANTERO RESOURCES Corp | B6: 2017 | C6: 15261490 | D6: 6385354 | E6: =C6-D6 -> 8876136 | F6: 3655574 | G6: 2915481 | H6: =F6-G6 -> 740093 | I6: 615070 | J6: 1.95 | K6: 2006291 | L6: 2461630 | M6: -2461630 | N6: =K6+M6 -> -455339 | O6: 452170 | P6: =K6-L6 -> -455339 | Q6: 19.24 | R6: =Q6/J6 -> 9.8666667 | S6: =I6/C6 -> 0.040302094 | T6: NASDAQ
A7: ANTERO RESOURCES Corp | B7: 2018 | C7: 15519464 | D7: 7031987 | E7: =C7-D7 -> 8487477 | F7: 4139626 | G7: 4067721 | H7: =F7-G7 -> 71905 | I7: -397517 | J7: -1.26 | K7: 2081987 | L7: 2350724 | M7: -2350724 | N7: =K7+M7 -> -268737 | O7: 240296 | P7: =K7-L7 -> -268737 | Q7: 9.2 | R7: =Q7/J7 -> -7.3015873 | S7: =I7/C7 -> -0.025614093 | T7: NASDAQ
A8: ANTERO RESOURCES Corp | B8: 2019 | C8: 15197569 | D8: 8226826 | E8: =C8-D8 -> 6970743 | F8: 4408690 | G8: 5395735 | H8: =F8-G8 -> -987045 | I8: -340129 | J8: -1.11 | K8: 1103458 | L8: 1041490 | M8: -1041490 | N8: =K8+M8 -> 61968 | O8: 557564 | P8: =K8-L8 -> 61968 | Q8: 2.88 | R8: =Q8/J8 -> -2.5945946 | S8: =I8/C8 -> -0.022380487 | T8: NASDAQ
A9: ANTERO RESOURCES Corp | B9: 2020 | C9: 13150845 | D9: 7060574 | E9: =C9-D9 -> 6090271 | F9: 3491699 | G9: 4445146 | H9: =F9-G9 -> -953447 | I9: -1267897 | J9: -4.65 | K9: 735640 | L9: 530061 | M9: -530061 | N9: =K9+M9 -> 205579 | O9: -205579 | P9: =K9-L9 -> 205579 | Q9: 5.57 | R9: =Q9/J9 -> -1.1978495 | S9: =I9/C9 -> -0.096411828 | T9: NASDAQ
A10: ANTERO RESOURCES Corp | B10: 2021 | C10: 13896528 | D10: 7830436 | E10: =C10-D10 -> 6066092 | F10: 4619432 | G10: 4595572 | H10: =F10-G10 -> 23860 | I10: -186899 | J10: -0.61 | K10: 1660116 | L10: 710784 | M10: -710784 | N10: =K10+M10 -> 949332 | O10: -949332 | P10: =K10-L10 -> 949332 | Q10: 17.33 | R10: =Q10/J10 -> -28.409836 | S10: =I10/C10 -> -0.013449331 | T10: NASDAQ
A11: ANTERO RESOURCES Corp | B11: 2022 | C11: 14118039 | D11: 7100885 | E11: =C11-D11 -> 7017154 | F11: 7138436 | G11: 4564531 | H11: =F11-G11 -> 2573905 | I11: 1898771 | J11: 6.18 | K11: 3051342 | L11: 943612 | M11: -943612 | N11: =K11+M11 -> 2107730 | O11: -2107730 | P11: =K11-L11 -> 2107730 | Q11: 29.95 | R11: =Q11/J11 -> 4.8462783 | S11: =I11/C11 -> 0.13449255 | T11: NASDAQ
A12: Callon Petroleum | B12: 2012 | C12: 378173 | D12: 172202 | E12: =C12-D12 -> 205971 | F12: 110733 | G12: 100043 | H12: =F12-G12 -> 10690 | I12: 2747 | J12: 0.07 | K12: 51290 | L12: 93703 | M12: -93703 | N12: =K12+M12 -> -42413 | O12: -243 | P12: =K12-L12 -> -42413 | Q12: 62.9 | R12: =Q12/J12 -> 898.57143 | S12: =I12/C12 -> 0.0072638713 | T12: NASDAQ
A13: Callon Petroleum | B13: 2013 | C13: 423953 | D13: 144859 | E13: =C13-D13 -> 279094 | F13: 102569 | G13: 91905 | H13: =F13-G13 -> 10664 | I13: -323 | J13: -0.01 | K13: 54329 | L13: 79804 | M13: -79804 | N13: =K13+M13 -> -25475 | O13: 27348 | P13: =K13-L13 -> -25475 | Q13: 37 | R13: =Q13/J13 -> -3700 | S13: =I13/C13 -> -0.00076187691 | T13: NASDAQ
... A19: Callon Petroleum | B19: 2019 | C19: 7194838 | D19: 3971530 | E19: =C19-D19 -> 3223308 | F19: 671572 | G19: 498914 | H19: =F19-G19 -> 172658 | I19: 55627 | J19: 0.24 | K19: 476316 | L19: 388389 | M19: -388389 | N19: =K19+M19 -> 87927 | O19: -90637 | P19: =K19-L19 -> 87927 | Q19: 75.5 | R19: =Q19/J19 -> 314.58333 | S19: =I19/C19 -> 0.0077315153 | T19: NASDAQ
A20: Callon Petroleum | B20: 2020 | C20: 4362868 | D20: 3651866 | E20: =C20-D20 -> 711002 | F20: 1033147 | G20: 3489999 | H20: =F20-G20 -> -2456852 | I20: -2533621 | J20: =-(63.79) -> -63.79 | K20: 559775 | L20: 529883 | M20: -529883 | N20: =K20+M20 -> 29892 | O20: 22997 | P20: =K20-L20 -> 29892 | Q20: 5.48 | R20: =Q20/J20 -> -0.085906882 | S20: =I20/C20 -> -0.58072373 | T20: NASDAQ
A21: Callon Petroleum | B21: 2021 | C21: 5547503 | D21: 3681735 | E21: =C21-D21 -> 1865768 | F21: 2045030 | G21: 1034977 | H21: =F21-G21 -> 1010053 | I21: 365151 | J21: 7.51 | K21: 974143 | L21: 876400 | M21: -876400 | N21: =K21+M21 -> 97743 | O21: 108097 | P21: =K21-L21 -> 97743 | Q21: 38.6 | R21: =Q21/J21 -> 5.1398136 | S21: =I21/C21 -> 0.065822587 | T21: NASDAQ
A22: Callon Petroleum | B22: 2022 | C22: 6146081 | D22: 3060659 | E22: =C22-D22 -> 3085422 | F22: 3230964 | G22: 1550432 | H22: =F22-G22 -> 1680532 | I22: 1209816 | J22: 19.63 | K22: 1501517 | L22: 999027 | M22: -999027 | N22: =K22+M22 -> 502490 | O22: -508977 | P22: =K22-L22 -> 502490 | Q22: 59.08 | R22: =Q22/J22 -> 3.0096791 | S22: =I22/C22 -> 0.19684348 | T22: NASDAQ
A23: Chesapeake Energy | B23: 2012 | C23: 41611000 | D23: 23715000 | E23: 17896000 | F23: 12316000 | G23: 14010000 | H23: -1694000 | I23: -940000 | J23: -1.46 | K23: 2837000 | L23: 4984000 | M23: -4984000 | N23: =K23+M23 -> -2147000 | O23: 2083000 | P23: =K23-L23 -> -2147000 | Q23: 0 | R23: =Q23/J23 -> 0 | S23: =I23/F23 -> -0.076323482 | T23: NASDAQ
A24: Chesapeake Energy | B24: 2013 | C24: 41782000 | D24: 23642000 | E24: 18140000 | F24: 17506000 | G24: 15437000 | H24: 2069000 | I24: 474000 | J24: 0.73 | K24: 4614000 | L24: 2967000 | M24: -2967000 | N24: =K24+M24 -> 1647000 | O24: -1097000 | P24: =K24-L24 -> 1647000 | Q24: 0 | R24: =Q24/J24 -> 0 | S24: =I24/C24 -> 0.011344598 | T24: NASDAQ
A25: Chesapeake Energy | B25: 2014 | C25: 40751000 | D25: 22546000 | E25: 18205000 | F25: 20951000 | G25: 17474000 | H25: 3477000 | I25: 1273000 | J25: 1.93 | K25: 4634000 | L25: 454000 | M25: -454000 | N25: =K25+M25 -> 4180000 | O25: -1817000 | P25: =K25-L25 -> 4180000 | Q25: 0 | R25: =Q25/J25 -> 0 | S25: =I25/C25 -> 0.031238497 | T25: NASDAQ
A26: Chesapeake Energy | B26: 2015 | C26: 17357000 | D26: 14960000 | E26: 2397000 | F26: 12764000 | G26: 31683000 | H26: -18919000 | I26: -14856000 | J26: -22.43 | K26: 1234000 | L26: 3451000 | M26: -3451000 | N26: =K26+M26 -> -2217000 | O26: -1066000 | P26: =K26-L26 -> -2217000 | Q26: 0 | R26: =Q26/J26 -> 0 | S26: =I26/C26 -> -0.85590828 | T26: NASDAQ
A27: Chesapeake Energy | B27: 2016 | C27: 13028000 | D27: 14231000 | E27: -1203000 | F27: 7872000 | G27: 12283000 | H27: -4411000 | I27: -4926000 | J27: -6.45 | K27: -204000 | L27: 660000 | M27: -660000 | N27: =K27+M27 -> -864000 | O27: 921000 | P27: =K27-L27 -> -864000 | Q27: 0 | R27: =Q27/J27 -> 0 | S27: =I27/C27 -> -0.37810869 | T27: NASDAQ
A28: Chesapeake Energy | B28: 2017 | C28: 12425000 | D28: 12797000 | E28: -372000 | F28: 9496000 | G28: 8357000 | H28: 1139000 | I28: 813000 | J28: 0.9 | K28: 745000 | L28: 1188000 | M28: -1188000 | N28: =K28+M28 -> -443000 | O28: -434000 | P28: =K28-L28 -> -443000 | Q28: 0 | R28: =Q28/J28 -> 0 | S28: =I28/C28 -> 0.065432596 | T28: NASDAQ
A29: Chesapeake Energy | B29: 2018 | C29: 10947000 | D29: 10480000 | E29: 467000 | F29: 10231000 | G29: 9349000 | H29: 882000 | I29: 775000 | J29: 0.85 | K29: 2000000 | L29: 185000 | M29: -185000 | N29: =K29+M29 -> 1815000 | O29: -2186000 | P29: =K29-L29 -> 1815000 | Q29: 0 | R29: =Q29/J29 -> 0 | S29: =I29/C29 -> 0.070795652 | T29: NASDAQ
A30: Chesapeake Energy | B30: 2019 | C30: 16193000 | D30: 11792000 | E30: 4401000 | F30: 8595000 | G30: 8626000 | H30: -31000 | I30: -416000 | J30: -0.25 | K30: 1623000 | L30: 2480000 | M30: -2480000 | N30: =K30+M30 -> -857000 | O30: 859000 | P30: =K30-L30 -> -857000 | Q30: 0 | R30: =Q30/J30 -> 0 | S30: =I30/C30 -> -0.025690113 | T30: NASDAQ
A31: Chesapeake Energy | B31: 2020 | C31: 6584000 | D31: 11925000 | E31: -5341000 | F31: 5296000 | G31: 13999000 | H31: -8703000 | I31: -9750000 | J31: -998.26 | K31: 1164000 | L31: 992000 | M31: -992000 | N31: =K31+M31 -> 172000 | O31: 101000 | P31: =K31-L31 -> 172000 | Q31: 0 | R31: =Q31/J31 -> 0 | S31: =I31/C31 -> -1.4808627 | T31: NASDAQ
A32: Chesapeake Energy | B32: 2021 | C32: 11009000 | D32: 5338000 | E32: 5671000 | F32: 5549000 | G32: 4611000 | H32: 938000 | I32: 945000 | J32: 9.29 | K32: 1809000 | L32: 850000 | M32: -850000 | N32: =K32+M32 -> 959000 | O32: -171000 | P32: =K32-L32 -> 959000 | Q32: 0 | R32: =Q32/J32 -> 0 | S32: =I32/C32 -> 0.085838859 | T32: NASDAQ
A33: Chesapeake Energy | B33: 2022 | C33: 15468000 | D33: 6344000 | E33: 9124000 | F33: 11743000 | G33: 7963000 | H33: 3780000 | I33: 4936000 | J33: 38.71 | K33: 4125000 | L33: 3401000 | M33: -3401000 | N33: =K33+M33 -> 724000 | O33: -1446000 | P33: =K33-L33 -> 724000 | Q33: 0 | R33: =Q33/J33 -> 0 | S33: =I33/C33 -> 0.31911042 | T33: NASDAQ
A34: Chord Energy | B34: 2022 | C34: 6631081 | D34: 1951283 | E34: =C34-D34 -> 4679798 | F34: 3646794 | G34: =2067872-4867 -> 2063005 | H34: =F34-G34 -> 1583789 | I34: 1856159 | J34: 60.86 | K34: 1924026 | L34: 682562 | M34: -682562 | N34: =K34+M34 -> 1241464 | O34: -823096 | P34: =K34-L34 -> 1241464 | Q34: 146.3 | R34: =Q34/J34 -> 2.4038778 | S34: =I34/C34 -> 0.27991801 | T34: NASDAQ
A35: Civitas Resources | B35: 2021 | C35: 6741033 | D35: 2086035 | E35: =C35-D35 -> 4654998 | F35: 930614 | G35: 608551 | H35: =F35-G35 -> 322063 | I35: 178921 | J35: 4.82 | K35: 274599 | L35: -73547 | M35: 73547 | N35: =K35+M35 -> 348146 | O35: -118435 | P35: =K35-L35 -> 348146 | Q35: 35.73 | R35: =Q35/J35 -> 7.4128631 | S35: =I35/C35 -> 0.026542074 | T35: NASDAQ
A36: Civitas Resources | B36: 2022 | C36: 7971399 | D36: 1177927 | E36: =C36-D36 -> 6793472 | F36: 3791398 | G36: 1807358 | H36: =F36-G36 -> 1984040 | I36: 1248080 | J36: 14.68 | K36: 2477041 | L36: 1306095 | M36: -1306095 | N36: =K36+M36 -> 1170946 | O36: -657368 | P36: =K36-L36 -> 1170946 | Q36: 59.71 | R36: =Q36/J36 -> 4.0674387 | S36: =I36/C36 -> 0.15656976 | T36: NASDAQ
A37: ConocoPhillips | B37: 2012 | C37: 117144000 | D37: =68717000 -> 68717000 | E37: =C37-D37 -> 48427000 | F37: 62004000 | G37: 46581000 | H37: =F37-G37 -> 15423000 | I37: 8428000 | J37: 6.77 | K37: 13922000 | L37: 11627000 | M37: -11627000 | N37: =K37+M37 -> 2295000 | O37: -4481 | P37: =K37-L37 -> 2295000 | Q37: 57.94 | R37: =Q37/J37 -> 8.5583456 | S37: =I37/C37 -> 0.07194564 | T37: NASDAQ
A38: ConocoPhillips | B38: 2013 | C38: 118057000 | D38: 65565000 | E38: =C38-D38 -> 52492000 | F38: 58248000 | G38: 43802000 | H38: =F38-G38 -> 14446000 | I38: 9156000 | J38: 7.43 | K38: 16087000 | L38: 6251000 | M38: -6251000 | N38: =K38+M38 -> 9836000 | O38: -7133000 | P38: =K38-L38 -> 9836000 | Q38: 60.1 | R38: =Q38/J38 -> 8.0888291 | S38: =I38/C38 -> 0.077555757 | T38: NASDAQ
A39: ConocoPhillips | B39: 2014 | C39: 116539000 | D39: 64266000 | E39: =C39-D39 -> 52273000 | F39: 55517000 | G39: 46127000 | H39: =F39-G39 -> 9390000 | I39: -6869 | J39: 5.54 | K39: 16735000 | L39: 15131000 | M39: -15131000 | N39: =K39+M39 -> 1604000 | O39: 2574000 | P39: =K39-L39 -> 1604000 | Q39: 70.35 | R39: =Q39/J39 -> 12.698556 | S39: =I39/C39 -> -5.8941642e-05 | T39: NASDAQ
A40: ConocoPhillips | B40: 2015 | C40: 97484000 | D40: 57402000 | E40: =C40-D40 -> 40082000 | F40: 30935000 | G40: 38174000 | H40: =F40-G40 -> -7239000 | I40: -4428000 | J40: -3.58 | K40: 7572000 | L40: 8655000 | M40: -8655000 | N40: =K40+M40 -> -1083000 | O40: -1429000 | P40: =K40-L40 -> -1083000 | Q40: 62.26 | R40: =Q40/J40 -> -17.391061 | S40: =I40/C40 -> -0.045422839 | T40: NASDAQ
A41: ConocoPhillips | B41: 2016 | C41: 89772000 | D41: 54546000 | E41: =C41-D41 -> 35226000 | F41: 24360000 | G41: 29890000 | H41: =F41-G41 -> -5530000 | I41: -3615000 | J41: -2.91 | K41: 4403000 | L41: 3859000 | M41: -3859000 | N41: =K41+M41 -> 544000 | O41: 764000 | P41: =K41-L41 -> 544000 | Q41: 40.27 | R41: =Q41/J41 -> -13.838488 | S41: =I41/C41 -> -0.040268681 | T41: NASDAQ
A42: ConocoPhillips | B42: 2017 | C42: 73362000 | D42: 42561000 | E42: =C42-D42 -> 30801000 | F42: 32584000 | G42: 35199000 | H42: =F42-G42 -> -2615000 | I42: -855000 | J42: -0.7 | K42: 7077000 | L42: -7762000 | M42: 7762000 | N42: =K42+M42 -> 14839000 | O42: -12356000 | P42: =K42-L42 -> 14839000 | Q42: 49.87 | R42: =Q42/J42 -> -71.242857 | S42: =I42/C42 -> -0.011654535 | T42: NASDAQ
A43: ConocoPhillips | B43: 2018 | C43: 69980000 | D43: 37916000 | E43: =C43-D43 -> 32064000 | F43: 38727000 | G43: 28754000 | H43: =F43-G43 -> 9973000 | I43: 6305000 | J43: 5.36 | K43: 12934000 | L43: 3843000 | M43: -3843000 | N43: =K43+M43 -> 9091000 | O43: -9359000 | P43: =K43-L43 -> 9091000 | Q43: 59.29 | R43: =Q43/J43 -> 11.061567 | S43: =I43/C43 -> 0.090097171 | T43: NASDAQ
A44: ConocoPhillips | B44: 2019 | C44: 70514000 | D44: 35464000 | E44: =C44-D44 -> 35050000 | F44: 36670000 | G44: 27146000 | H44: =F44-G44 -> 9524000 | I44: 7189000 | J44: 6.43 | K44: 11104000 | L44: 6618000 | M44: -6618000 | N44: =K44+M44 -> 4486000 | O44: -5229000 | P44: =K44-L44 -> 4486000 | Q44: 66.74 | R44: =Q44/J44 -> 10.379471 | S44: =I44/F44 -> 0.19604581 | T44: NASDAQ
A45: ConocoPhillips | B45: 2020 | C45: 22396000 | D45: 32769000 | E45: =C45-D45 -> -10373000 | F45: 19256000 | G45: 22396000 | H45: =F45-G45 -> -3140000 | I45: -2701000 | J45: -2.51 | K45: 4802000 | L45: 4121000 | M45: -4121000 | N45: =K45+M45 -> 681000 | O45: -2708000 | P45: =K45-L45 -> 681000 | Q45: 30.8 | R45: =Q45/J45 -> -12.270916 | S45: =I45/F45 -> -0.14026797 | T45: NASDAQ
A46: ConocoPhillips | B46: 2021 | C46: 90661000 | D46: 45255000 | E46: =C46-D46 -> 45406000 | F46: 48349000 | G46: 35637000 | H46: =F46-G46 -> 12712000 | I46: 8079000 | J46: 6.09 | K46: 16996000 | L46: 8544000 | M46: -8544000 | N46: =K46+M46 -> 8452000 | O46: -6335000 | P46: =K46-L46 -> 8452000 | Q46: 52.97 | R46: =Q46/J46 -> 8.6978654 | S46: =I46/C46 -> 0.089112187 | T46: NASDAQ
A47: ConocoPhillips | B47: 2022 | C47: 93829000 | D47: 45826000 | E47: =C47-D47 -> 48003000 | F47: 82156000 | G47: 53928000 | H47: =F47-G47 -> 28228000 | I47: 18680000 | J47: 14.62 | K47: 28314000 | L47: 8741000 | M47: -8741000 | N47: =K47+M47 -> 19573000 | O47: -18053000 | P47: =K47-L47 -> 19573000 | Q47: 100 | R47: =Q47/J47 -> 6.8399453 | S47: =I47/C47 -> 0.19908557 | T47: NASDAQ
A48: Coterra Energy Inc. | B48: 2021 | C48: 19900000 | D48: 8112000 | E48: =C48-D48 -> 11788000 | F48: 3449000 | G48: 1883000 | H48: =F48-G48 -> 1566000 | I48: 1158000 | J48: 2.3 | K48: 1667000 | L48: -313000 | M48: 313000 | N48: =K48+M48 -> 1980000 | O48: -1086000 | P48: =K48-L48 -> 1980000 | Q48: 18.78 | R48: =Q48/J48 -> 8.1652174 | S48: =I48/C48 -> 0.058190955 | T48: NASDAQ
A49: Coterra Energy Inc. | B49: 2022 | C49: 20154000 | D49: 7484000 | E49: =C49-D49 -> 12670000 | F49: 9051000 | G49: 5209000 | H49: =F49-G49 -> 3842000 | I49: 4065000 | J49: 5.09 | K49: 5456000 | L49: 1674000 | M49: -1674000 | N49: =K49+M49 -> 3782000 | O49: -4145000 | P49: =K49-L49 -> 3782000 | Q49: 26.97 | R49: =Q49/J49 -> 5.2986248 | S49: =I49/C49 -> 0.20169693 | T49: NASDAQ
A50: Crescent Energy Co | B50: 2017 | C50: 16005000 | D50: 6842000 | E50: =C50-D50 -> 9163000 | F50: 2796000 | G50: 2819000 | H50: =F50-G50 -> -23000 | I50: -124000 | J50: -0.23 | K50: 1718000 | L50: 1960000 | M50: -1960000 | N50: =K50+M50 -> -242000 | O50: 291200 | P50: =K50-L50 -> -242000 | Q50: 10.78 | R50: =Q50/J50 -> -46.869565 | S50: =I50/C50 -> -0.0077475789 | T50: NASDAQ
A51: Crescent Energy Co | B51: 2018 | C51: 12730000 | D51: 6117000 | E51: =C51-D51 -> 6613000 | F51: 3356000 | G51: 6912000 | H51: =F51-G51 -> -3556000 | I51: -2377000 | J51: -4.77 | K51: 1748000 | L51: 1509000 | M51: -1509000 | N51: =K51+M51 -> 239000 | O51: -287900 | P51: =K51-L51 -> 239000 | Q51: 6.78 | R51: =Q51/J51 -> -1.4213836 | S51: =I51/C51 -> -0.18672427 | T51: NASDAQ
A52: Crescent Energy Co | B52: 2019 | C52: 10091800 | D52: 4749100 | E52: =C52-D52 -> 5342700 | F52: 2656200 | G52: 3848500 | H52: =F52-G52 -> -1192300 | I52: -1129500 | J52: -1.89 | K52: 1742900 | L52: 345000 | M52: -345000 | N52: =K52+M52 -> 1397900 | O52: -1355700 | P52: =K52-L52 -> 1397900 | Q52: 3.23 | R52: =Q52/J52 -> -1.7089947 | S52: =I52/C52 -> -0.11192255 | T52: NASDAQ
A53: Crescent Energy Co | B53: 2020 | C53: 6645900 | D53: 3823100 | E53: =C53-D53 -> 2822800 | F53: 2003600 | G53: 5151100 | H53: =F53-G53 -> -3147500 | I53: -2497.7 | J53: -4.76 | K53: 860500 | L53: 269000 | M53: -269000 | N53: =K53+M53 -> 591500 | O53: 639500 | P53: =K53-L53 -> 591500 | Q53: 0.77 | R53: =Q53/J53 -> -0.16176471 | S53: =I53/C53 -> -0.0003758257 | T53: NASDAQ
A54: Crescent Energy Co | B54: 2021 | C54: 9171200 | D54: 3765900 | E54: =C54-D54 -> 5405300 | F54: 2439900 | G54: -723900 | H54: =F54-G54 -> 3163800 | I54: 2376000 | J54: 4.15 | K54: 1495800 | L54: 1193400 | M54: -1193400 | N54: =K54+M54 -> 302400 | O54: 297200 | P54: =K54-L54 -> 302400 | Q54: 4.16 | R54: =Q54/J54 -> 1.0024096 | S54: =I54/C54 -> 0.25907188 | T54: NASDAQ
A55: Crescent Energy Co | B55: 2022 | C55: 9486400 | D55: 2993000 | E55: =C55-D55 -> 6493400 | F55: 3578400 | G55: 1707100 | H55: =F55-G55 -> 1871300 | I55: 1574100 | J55: 2.62 | K55: 2192200 | L55: 860600 | M55: -860600 | N55: =K55+M55 -> 1331600 | O55: -1056000 | P55: =K55-L55 -> 1331600 | Q55: 7.23 | R55: =Q55/J55 -> 2.759542 | S55: =I55/C55 -> 0.16593228 | T55: NASDAQ
A56: Crescent Energy Co | B56: 2016 | C56: 16163600 | D56: 842500 | E56: =C56-D56 -> 15321100 | F56: 1939900 | G56: 3253700 | H56: =F56-G56 -> -1313800 | I56: -992000 | J56: -1.81 | K56: 1524300 | L56: 1360400 | M56: -1360400 | N56: =K56+M56 -> 163900 | O56: -175600 | P56: =K56-L56 -> 163900 | Q56: 13.79 | R56: =Q56/J56 -> -7.6187845 | S56: =I56/C56 -> -0.061372467 | T56: NASDAQ
A57: Devon Energy Corporation | B57: 2017 | C57: 30241000 | D57: =C57-E57 -> 16137000 | E57: 14104000 | F57: 13949000 | G57: 13053000 | H57: =F57-G57 -> 896000 | I57: 1010000 | J57: 1.71 | K57: 2909000 | L57: 2210000 | M57: -2210000 | N57: =K57+M57 -> 699000 | O57: 9000 | P57: =K57-L57 -> 699000 | Q57: 41.72 | R57: =Q57/J57 -> 24.397661 | S57: =I57/C57 -> 0.033398366 | T57: NASDAQ
A58: Devon Energy Corporation | B58: 2018 | C58: 19566000 | D58: =C58-E58 -> 10380000 | E58: 9186000 | F58: 10734000 | G58: 9814000 | H58: =F58-G58 -> 920000 | I58: 3064000 | J58: 1.53 | K58: 2228000 | L58: 1493000 | M58: -1493000 | N58: =K58+M58 -> 735000 | O58: -4386000 | P58: =K58-L58 -> 735000 | Q58: 31.79 | R58: =Q58/J58 -> 20.777778 | S58: =I58/C58 -> 0.15659818 | T58: NASDAQ
A59: Devon Energy Corporation | B59: 2019 | C59: 13717000 | D59: =C59-E59 -> 7915000 | E59: 5802000 | F59: 6220000 | G59: 6329000 | H59: =F59-G59 -> -109000 | I59: -353000 | J59: 0.89 | K59: 2043000 | L59: -1551000 | M59: -1551000 | N59: =K59+M59 -> 492000 | O59: -2061000 | P59: =K59-L59 -> 3594000 | Q59: 31.556 | R59: =Q59/J59 -> 35.45618 | S59: =I59/C59 -> -0.02573449 | T59: NASDAQ
A60: Devon Energy Corporation | B60: 2020 | C60: 9912000 | D60: =C60-E60 -> 6893000 | E60: 3019000 | F60: 4828000 | G60: 7918000 | H60: =F60-G60 -> -3090000 | I60: -2680000 | J60: -7.12 | K60: 1464000 | M60: -1127000 | N60: =K60+M60 -> 337000 | O60: -306000 | P60: =K60-L60 -> 1464000 | Q60: 6.91 | R60: =Q60/J60 -> -0.97050562 | S60: =I60/C60 -> -0.27037934 | T60: NASDAQ
A61: Devon Energy Corporation | B61: 2021 | C61: 21025000 | D61: =C61-E61 -> 11626000 | E61: 9399000 | F61: 12206000 | G61: 9308000 | H61: =F61-G61 -> 2898000 | I61: 2813000 | J61: 4.2 | K61: 4899000 | M61: -1574000 | N61: =K61+M61 -> 3325000 | O61: -3292000 | P61: =K61-L61 -> 4899000 | Q61: 21.85 | R61: =Q61/J61 -> 5.202381 | S61: =I61/C61 -> 0.1337931 | T61: NASDAQ
A62: Devon Energy Corporation | B62: 2022 | C62: 23721000 | D62: =C62-E62 -> 12425000 | E62: 11296000 | F62: 19169000 | G62: 11394000 | H62: =F62-G62 -> 7775000 | I62: 6015000 | J62: 9.15 | K62: 8530000 | M62: -5123000 | N62: =K62+M62 -> 3407000 | O62: -4213000 | P62: =K62-L62 -> 8530000 | Q62: 59.13 | R62: =Q62/J62 -> 6.4622951 | S62: =I62/C62 -> 0.25357278 | T62: NASDAQ
A63: Diamondback Energy, Inc. | B63: 2020 | C63: 17619000 | D63: 1236000 | E63: =C63-D63 -> 16383000 | F63: 2813000 | G63: 8289000 | H63: =F63-G63 -> -5476000 | I63: -4672000 | J63: -28.59 | K63: 2118000 | M63: -2101000 | N63: =K63+M63 -> 17000 | O63: -37000 | P63: =K63-L63 -> 2118000 | Q63: 26.2 | R63: =Q63/J63 -> -0.91640434 | S63: =I63/C63 -> -0.26516828 | T63: NASDAQ
A64: Diamondback Energy, Inc. | B64: 2021 | C64: 22898000 | D64: 9653000 | E64: =C64-D64 -> 13245000 | F64: 6797000 | G64: 2796000 | H64: =F64-G64 -> 4001000 | I64: 2276000 | J64: 12.35 | K64: 3944000 | M64: -1539000 | N64: =K64+M64 -> 2405000 | O64: -1841000 | P64: =K64-L64 -> 3944000 | Q64: 73.49 | R64: =Q64/J64 -> 5.9506073 | S64: =I64/C64 -> 0.099397327 | T64: NASDAQ
A65: Diamondback Energy, Inc. | B65: 2022 | C65: 26209000 | D65: 10519000 | E65: =C65-D65 -> 15690000 | F65: 9643000 | G65: 3135000 | H65: =F65-G65 -> 6508000 | I65: 4562000 | J65: 24.61 | K65: 6325000 | M65: -3330000 | N65: =K65+M65 -> 2995000 | O65: -3503 | P65: =K65-L65 -> 6325000 | Q65: 137.08 | R65: =Q65/J65 -> 5.5700935 | S65: =I65/C65 -> 0.17406234 | T65: NASDAQ
A66: Diversified Energy | B66: 2015 | C66: 46487 | D66: 55304 | E66: =C66-D66 -> -8817 | F66: 6304 | G66: 4251 | H66: =F66-G66 -> 2053 | I66: -396 | J66: 0.01 | K66: -3931 | M66: -3649 | N66: =K66+M66 -> -7580 | O66: 7636 | P66: =K66-L66 -> -3931 | Q66: 0 | R66: =Q66/J66 -> 0 | S66: =I66/C66 -> -0.0085185106 | T66: NASDAQ
A67: Diversified Energy | B67: 2016 | C67: 85875 | D67: 76713 | E67: =C67-D67 -> 9162 | F67: 18279 | G67: 12767 | H67: =F67-G67 -> 5512 | I67: 18583 | J67: 0.42 | K67: 5129 | M67: -9209 | N67: =K67+M67 -> -4080 | O67: 4214 | P67: =K67-L67 -> 5129 | Q67: 0 | R67: =Q67/J67 -> 0 | S67: =I67/C67 -> 0.21639592 | T67: NASDAQ
A68: Diversified Energy | B68: 2017 | C68: 228683 | D68: 139024 | E68: =C68-D68 -> 89659 | F68: 41777 | G68: 20908 | H68: =F68-G68 -> 20869 | I68: 9230 | J68: 0.07 | K68: 6922 | M68: -93091 | N68: =K68+M68 -> -86169 | O68: 101113 | P68: =K68-L68 -> 6922 | Q68: 0 | R68: =Q68/J68 -> 0 | S68: =I68/C68 -> 0.040361549 | T68: NASDAQ
A69: Diversified Energy | B69: 2018 | C69: 1556972 | D69: 808109 | E69: =C69-D69 -> 748863 | F69: 289769 | G69: 107793 | H69: =F69-G69 -> 181976 | I69: 201120 | J69: 0.52 | K69: 87735 | M69: -766849 | N69: =K69+M69 -> -679114 | O69: 665318 | P69: =K69-L69 -> 87735 | Q69: 0 | R69: =Q69/J69 -> 0 | S69: =I69/C69 -> 0.12917381 | T69: NASDAQ
A70: Diversified Energy | B70: 2019 | C70: 2005940 | D70: 1067805 | E70: =C70-D70 -> 938135 | F70: 462256 | G70: 202385 | H70: =F70-G70 -> 259871 | I70: 99400 | J70: 0.15 | K70: 279156 | M70: -466887 | N70: =K70+M70 -> -187731 | O70: 188020 | P70: =K70-L70 -> 279156 | Q70: 1.5 | R70: =Q70/J70 -> 10 | S70: =I70/C70 -> 0.049552828 | T70: NASDAQ
A71: Diversified Energy | B71: 2020 | C71: 2290682 | D71: 1404024 | E71: =C71-D71 -> 886658 | F71: 408693 | G71: 203963 | H71: =F71-G71 -> 204730 | I71: -23502 | J71: -0.03 | K71: 241710 | M71: -256863 | N71: =K71+M71 -> -15153 | O71: 14871 | P71: =K71-L71 -> 241710 | Q71: 0.89 | R71: =Q71/J71 -> -29.666667 | S71: =I71/C71 -> -0.010259827 | T71: NASDAQ
A72: Diversified Energy | B72: 2021 | C72: 3494209 | D72: 2830259 | E72: =C72-D72 -> 663950 | F72: 1007561 | G72: 291213 | H72: =F72-G72 -> 716348 | I72: -325206 | J72: -0.41 | K72: 320182 | M72: -625874 | N72: =K72+M72 -> -305692 | O72: 316871 | P72: =K72-L72 -> 320182 | Q72: 1.64 | R72: =Q72/J72 -> -4 | S72: =I72/C72 -> -0.093069991 | T72: NASDAQ
A73: Diversified Energy | B73: 2022 | C73: 3830928 | D73: 3968652 | E73: =C73-D73 -> -137724 | F73: 1919349 | G73: -445893 | H73: =F73-G73 -> 2365242 | I73: -620598 | J73: -0.74 | K73: 387764 | M73: -386457 | N73: =K73+M73 -> 1307 | O73: -6536 | P73: =K73-L73 -> 387764 | Q73: 1.58 | R73: =Q73/J73 -> -2.1351351 | S73: =I73/C73 -> -0.16199678 | T73: NASDAQ
A74: Enerplus Resources (USA) Corporation | B74: 2012 | C74: 5412162 | D74: 2362608 | E74: =C74-D74 -> 3049554 | F74: 1188706 | G74: 1405673 | H74: =F74-G74 -> -216967 | I74: -310722 | J74: -0.8 | K74: 535077 | M74: -747604 | N74: =K74+M74 -> -212527 | O74: 210468 | P74: =K74-L74 -> 535077 | Q74: 22.42 | R74: =Q74/J74 -> -28.025 | S74: =I74/C74 -> -0.057411807 | T74: NASDAQ
... A84: Enerplus Resources (USA) Corporation | B84: 2022 | C84: 1937981 | D84: 861368 | E84: =C84-D84 -> 1076613 | F84: 2155688 | G84: 948090 | H84: =F84-G84 -> 1207598 | I84: 914302 | J84: 3.91 | K84: 1173382 | M84: -289672 | N84: =K84+M84 -> 883710 | O84: -908144 | P84: =K84-L84 -> 1173382 | Q84: 12.7 | R84: =Q84/J84 -> 3.2480818 | S84: =I84/C84 -> 0.47178068 | T84: NASDAQ
A85: EOG Resources, Inc. | B85: 2012 | C85: 27336578 | D85: =C85-E85 -> 14051814 | E85: 13284764 | F85: 11682636 | G85: 10202839 | H85: =F85-G85 -> 1479797 | I85: 570279 | J85: 2.13 | K85: 5236777 | M85: -6119263 | N85: =K85+M85 -> -882486 | O85: 1139751 | P85: =K85-L85 -> 5236777 | Q85: 55.04 | R85: =Q85/J85 -> 25.840376 | S85: =I85/C85 -> 0.020861389 | T85: NASDAQ
A86: EOG Resources, Inc. | B86: 2013 | C86: 30574238 | D86: =C86-E86 -> 15155779 | E86: 15418459 | F86: 14487118 | G86: 10811907 | H86: =F86-G86 -> 3675211 | I86: 2197109 | J86: 4.07 | K86: 7329414 | M86: -6314778 | N86: =K86+M86 -> 1014636 | O86: -573926 | P86: =K86-L86 -> 7329414 | Q86: 63.45 | R86: =Q86/J86 -> 15.589681 | S86: =I86/C86 -> 0.071861448 | T86: NASDAQ
A87: EOG Resources, Inc. | B87: 2014 | C87: 34762687 | D87: =C87-E87 -> 17050105 | E87: 17712582 | F87: 18035340 | G87: 12793517 | H87: =F87-G87 -> 5241823 | I87: 2915487 | J87: 5.36 | K87: 8649155 | M87: -7513565 | N87: =K87+M87 -> 1135590 | O87: -327734 | P87: =K87-L87 -> 8649155 | Q87: 48.59 | R87: =Q87/J87 -> 9.0652985 | S87: =I87/C87 -> 0.083868287 | T87: NASDAQ
A88: EOG Resources, Inc. | B88: 2015 | C88: 26975244 | D88: =C88-E88 -> 14032209 | E88: 12943035 | F88: 8757428 | G88: 15443507 | H88: =F88-G88 -> -6686079 | I88: -4524515 | J88: -8.29 | K88: 3595165 | M88: -5320256 | N88: =K88+M88 -> -1725091 | O88: -370921 | P88: =K88-L88 -> 3595165 | Q88: 90.85 | R88: =Q88/J88 -> -10.958987 | S88: =I88/C88 -> -0.16772842 | T88: NASDAQ
A89: EOG Resources, Inc. | B89: 2016 | C89: 29459433 | D89: =C89-E89 -> 15477852 | E89: 13981581 | F89: 7650632 | G89: 8875913 | H89: =F89-G89 -> -1225281 | I89: -1096686 | J89: -1.98 | K89: 2359063 | M89: -1252944 | N89: =K89+M89 -> 1106119 | O89: -242722 | P89: =K89-L89 -> 2359063 | Q89: 71.92 | R89: =Q89/J89 -> -36.323232 | S89: =I89/C89 -> -0.037226989 | T89: NASDAQ
A90: EOG Resources, Inc. | B90: 2017 | C90: 29833078 | D90: =C90-E90 -> 13549805 | E90: 16283273 | F90: 11208320 | G90: 10281918 | H90: =F90-G90 -> 926402 | I90: 2582579 | J90: 4.49 | K90: 4265336 | M90: -3987409 | N90: =K90+M90 -> 277927 | O90: -1035711 | P90: =K90-L90 -> 4265336 | Q90: 96.66 | R90: =Q90/J90 -> 21.52784 | S90: =I90/C90 -> 0.086567635 | T90: NASDAQ
A91: EOG Resources, Inc. | B91: 2018 | C91: 33934474 | D91: =C91-E91 -> 14570286 | E91: 19364188 | F91: 17275399 | G91: 12806053 | H91: =F91-G91 -> 4469346 | I91: 3419040 | J91: 5.93 | K91: 7768608 | M91: -6170162 | N91: =K91+M91 -> 1598446 | O91: -839103 | P91: =K91-L91 -> 7768608 | Q91: 104 | R91: =Q91/J91 -> 17.537943 | S91: =I91/C91 -> 0.10075418 | T91: NASDAQ
A92: EOG Resources, Inc. | B92: 2019 | C92: 37124608 | D92: =C92-E92 -> 15483892 | E92: 21640716 | F92: 17379973 | G92: 13680962 | H92: =F92-G92 -> 3699011 | I92: 2734910 | J92: 4.73 | K92: 8163180 | M92: -6177173 | N92: =K92+M92 -> 1986007 | O92: -1513321 | P92: =K92-L92 -> 8163180 | Q92: 94.38 | R92: =Q92/J92 -> 19.953488 | S92: =I92/C92 -> 0.073668387 | T92: NASDAQ
A93: EOG Resources, Inc. | B93: 2020 | C93: 35804601 | D93: =C93-E93 -> 15502714 | E93: 20301887 | F93: 11032000 | G93: 11576000 | H93: =F93-G93 -> -544000 | I93: -605000 | J93: -1.04 | K93: 5008 | M93: -3348 | N93: =K93+M93 -> 1660 | O93: -359 | P93: =K93-L93 -> 5008 | Q93: 35.59 | R93: =Q93/J93 -> -34.221154 | S93: =I93/C93 -> -0.01689727 | T93: NASDAQ
A94: EOG Resources, Inc. | B94: 2021 | C94: 38236000 | D94: =C94-E94 -> 16056000 | E94: 22180000 | F94: 18642000 | G94: 12540000 | H94: =F94-G94 -> 6102000 | I94: 4664000 | J94: 8.03 | K94: 8791 | M94: -3419 | N94: =K94+M94 -> 5372 | O94: -3493 | P94: =K94-L94 -> 8791 | Q94: 71.87 | R94: =Q94/J94 -> 8.9501868 | S94: =I94/C94 -> 0.12197929 | T94: NASDAQ
A95: EOG Resources, Inc. | B95: 2022 | C95: 41371000 | D95: =C95-E95 -> 16592000 | E95: 24779000 | F95: 25702000 | G95: 15736000 | H95: =F95-G95 -> 9966000 | I95: 7759000 | J95: 13.31 | K95: 11093 | M95: -5056 | N95: =K95+M95 -> 6037 | O95: -5273 | P95: =K95-L95 -> 11093 | Q95: 118.38 | R95: =Q95/J95 -> 8.8940646 | S95: =I95/C95 -> 0.18754683 | T95: NASDAQ
A96: EQT Corporation | B96: 2012 | C96: 8849862 | D96: 4961060 | E96: =C96-D96 -> 3888802 | F96: 1377222 | G96: 987593 | H96: =F96-G96 -> 389629 | I96: 183395 | J96: 0.91 | K96: 796822 | M96: -1370498 | N96: =K96+M96 -> -573676 | O96: -649196 | P96: =K96-L96 -> 796822 | Q96: 26.24 | R96: =Q96/J96 -> 28.835165 | S96: =I96/C96 -> 0.020722922 | T96: NASDAQ
A97: EQT Corporation | B97: 2013 | C97: 9792053 | D97: 4927925 | E97: =C97-D97 -> 4864128 | F97: 1862011 | G97: 1227025 | H97: =F97-G97 -> 634986 | I97: 390572 | J97: 1.98 | K97: 1162861 | M97: -999775 | N97: =K97+M97 -> 163086 | O97: 663586 | P97: =K97-L97 -> 1162861 | Q97: 36.88 | R97: =Q97/J97 -> 18.626263 | S97: =I97/C97 -> 0.039886631 | T97: NASDAQ
A98: EQT Corporation | B98: 2014 | C98: 12064900 | D98: 5691837 | E98: =C98-D98 -> 6373063 | F98: 2469710 | G98: 1650461 | H98: =F98-G98 -> 819249 | I98: 386965 | J98: 2.54 | K98: 1414742 | M98: -2444212 | N98: =K98+M98 -> -1029470 | O98: 231788 | P98: =K98-L98 -> 1414742 | Q98: 52.78 | R98: =Q98/J98 -> 20.779528 | S98: =I98/C98 -> 0.032073619 | T98: NASDAQ
A99: EQT Corporation | B99: 2015 | C99: 13976172 | D99: 5948130 | E99: =C99-D99 -> 8028042 | F99: 2339762 | G99: 1776623 | H99: =F99-G99 -> 563139 | I99: 85171 | J99: 0.56 | K99: 1216940 | M99: -2525607 | N99: =K99+M99 -> -1308667 | O99: 1832470 | P99: =K99-L99 -> 1216940 | Q99: 45.1 | R99: =Q99/J99 -> 80.535714 | S99: =I99/C99 -> 0.0060940149 | T99: NASDAQ
A100: EQT Corporation | B100: 2016 | C100: 15472922 | D100: 6353675 | E100: =C100-D100 -> 9119247 | F100: 1608348 | G100: 1894673 | H100: =F100-G100 -> -286325 | I100: -452983 | J100: -2.71 | K100: 1064320 | M100: -2961481 | N100: =K100+M100 -> -1897161 | O100: 1399469 | P100: =K100-L100 -> 1064320 | Q100: 36.6 | R100: =Q100/J100 -> -13.505535 | S100: =I100/C100 -> -0.029275854 | T100: NASDAQ
A101: EQT Corporation | B101: 2017 | C101: 29522604 | D101: 11107991 | E101: =C101-D101 -> 18414613 | F101: 3378015 | G101: 2445034 | H101: =F101-G101 -> 932981 | I101: 1508529 | J101: 8.05 | K101: 1637698 | M101: -4127070 | N101: =K101+M101 -> -2489372 | O101: 1533147 | P101: =K101-L101 -> 1637698 | Q101: 33.26 | R101: =Q101/J101 -> 4.131677 | S101: =I101/C101 -> 0.051097424 | T101: NASDAQ
A102: EQT Corporation | B102: 2018 | C102: 20721344 | D102: 9763115 | E102: =C102-D102 -> 10958229 | F102: 4557868 | G102: 7340992 | H102: =F102-G102 -> -2783124 | I102: -2244568 | J102: -9.12 | K102: 2976256 | M102: -3979104 | N102: =K102+M102 -> -1002848 | O102: 859020 | P102: =K102-L102 -> 2976256 | Q102: 25.86 | R102: =Q102/J102 -> -2.8355263 | S102: =I102/C102 -> -0.10832155 | T102: NASDAQ
A103: EQT Corporation | B103: 2019 | C103: 18809227 | D103: 9005639 | E103: =C103-D103 -> 9803588 | F103: 4416484 | G103: 5568594 | H103: =F103-G103 -> -1152110 | I103: -1221695 | J103: -4.79 | K103: 1851704 | M103: -1601142 | N103: =K103+M103 -> 250562 | O103: -249453 | P103: =K103-L103 -> 1851704 | Q103: 20.74 | R103: =Q103/J103 -> -4.3298539 | S103: =I103/C103 -> -0.064951898 | T103: NASDAQ
A104: EQT Corporation | B104: 2020 | C104: 18113469 | D104: 8850739 | E104: =C104-D104 -> 9262730 | F104: 3058843 | G104: 3936509 | H104: =F104-G104 -> -877666 | I104: 967166 | J104: -3.71 | K104: 1537701 | M104: -1555800 | N104: =K104+M104 -> -18099 | O104: 31713 | P104: =K104-L104 -> 1537701 | Q104: 7 | R104: =Q104/J104 -> -1.8867925 | S104: =I104/C104 -> 0.053394852 | T104: NASDAQ
A105: EQT Corporation | B105: 2021 | C105: 21607388 | D105: 11636389 | E105: =C105-D105 -> 9970999 | F105: 3064663 | G105: 4425638 | H105: =F105-G105 -> -1360975 | I105: -1142747 | J105: -3.54 | K105: 1662448 | M105: -2072742 | N105: =K105+M105 -> -410294 | O105: 506047 | P105: =K105-L105 -> 1662448 | Q105: 18.58 | R105: =Q105/J105 -> -5.2485876 | S105: =I105/C105 -> -0.052886864 | T105: NASDAQ
A106: EQT Corporation | B106: 2022 | C106: 22669926 | D106: 11456598 | E106: =C106-D106 -> 11213328 | F106: 7497689 | G106: 4779692 | H106: =F106-G106 -> 2717997 | I106: 1770965 | J106: 4.79 | K106: 3465560 | M106: -2072742 | N106: =K106+M106 -> 1392818 | O106: -699126 | P106: =K106-L106 -> 3465560 | Q106: 34.41 | R106: =Q106/J106 -> 7.1837161 | S106: =I106/C106 -> 0.078119576 | T106: NASDAQ
A107: Gulfport Energy Corporation | B107: 2012 | C107: 1578368 | D107: 451960 | E107: =C107-D107 -> 1126408 | F107: 248926 | G107: 151663 | H107: =F107-G107 -> 97263 | I107: 68371 | J107: 1.22 | K107: 199158 | M107: -840579 | N107: =K107+M107 -> -641421 | O107: 714612 | P107: =K107-L107 -> 199158 | Q107: 0 | R107: =Q107/J107 -> 0 | S107: =I107/C107 -> 0.043317528 | T107: NASDAQ
... A115: Gulfport Energy Corporation | B115: 2020 | C115: 2539871 | D115: 2840371 | E115: =C115-D115 -> -300500 | F115: 866542 | G115: 2229147 | H115: =F115-G115 -> -1362605 | I115: -1625133 | J115: -10.14 | K115: 95304 | M115: -314587 | N115: =K115+M115 -> -219283 | O115: 303084 | P115: =K115-L115 -> 95304 | Q115: 0 | R115: =Q115/J115 -> 0 | S115: =I115/C115 -> -0.63984864 | T115: NASDAQ
A116: Gulfport Energy Corporation | B116: 2021 | C116: 2168232 | D116: 1560858 | E116: =C116-D116 -> 607374 | F116: =535765+273037 -> 808802 | G116: =591691+290695 -> 882386 | H116: =F116-G116 -> -73584 | I116: =250994-117402 -> 133592 | J116: =1.56-5.71 -> -4.15 | K116: =292985+172155 -> 465140 | M116: =-200105-97831 -> -297936 | N116: =K116+M116 -> 167204 | O116: =-149037-104768 -> -253805 | P116: =K116-L116 -> 465140 | Q116: 64.7 | R116: =Q116/J116 -> -15.590361 | S116: =I116/C116 -> 0.061613333 | T116: NASDAQ
A117: Gulfport Energy Corporation | B117: 2022 | C117: 2534479 | D117: 1653349 | E117: =C117-D117 -> 881130 | F117: 1331112 | G117: 787986 | H117: =F117-G117 -> 543126 | I117: 412856 | J117: 20.45 | K117: 739077 | M117: -458295 | N117: =K117+M117 -> 280782 | O117: -276783 | P117: =K117-L117 -> 739077 | Q117: 89.82 | R117: =Q117/J117 -> 4.392176 | S117: =I117/C117 -> 0.16289581 | T117: NASDAQ
A118: Hess | B118: 2012 | C118: 43441000 | D118: 22238000 | E118: =C118-D118 -> 21203000 | F118: 12935000 | G118: 9598000 | H118: =F118-G118 -> 3337000 | I118: 2025000 | J118: 5.98 | K118: 5660000 | M118: -7051 | N118: =K118+M118 -> 5652949 | O118: 1682000 | P118: =K118-L118 -> 5660000 | Q118: 58.95 | R118: =Q118/J118 -> 9.8578595 | S118: =I118/C118 -> 0.046614949 | T118: NASDAQ
A119: Hess | B119: 2013 | C119: 42754000 | D119: 17970000 | E119: =C119-D119 -> 24784000 | F119: 14028000 | G119: 9427000 | H119: =F119-G119 -> 4601000 | I119: 5052000 | J119: 15.01 | K119: 4870000 | M119: 578000 | N119: =K119+M119 -> 5448000 | O119: -4276000 | P119: =K119-L119 -> 4870000 | Q119: 71.61 | R119: =Q119/J119 -> 4.7708195 | S119: =I119/C119 -> 0.11816438 | T119: NASDAQ
A120: Hess | B120: 2014 | C120: 38578000 | D120: 16258000 | E120: =C120-D120 -> 22320000 | F120: 11439000 | G120: 9003000 | H120: =F120-G120 -> 2436000 | I120: 2317000 | J120: 7.63 | K120: 4464000 | M120: 1000 | N120: =K120+M120 -> 4465000 | O120: -3835000 | P120: =K120-L120 -> 4464000 | Q120: 82.88 | R120: =Q120/J120 -> 10.862385 | S120: =I120/C120 -> 0.060060138 | T120: NASDAQ
A121: Hess | B121: 2015 | C121: 34195000 | D121: 13794000 | E121: =C121-D121 -> 20401000 | F121: 6561000 | G121: 10819000 | H121: =F121-G121 -> -4258000 | I121: -3056000 | J121: -10.78 | K121: 1981000 | M121: -4206000 | N121: =K121+M121 -> -2225000 | O121: 2497000 | P121: =K121-L121 -> 1981000 | Q121: 67.87 | R121: =Q121/J121 -> -6.2959184 | S121: =I121/C121 -> -0.089369791 | T121: NASDAQ
...

Sheet Sheet3
M9: =(325737/500) -> 651.474 | P9: =53*(1+0.1)^(2024-2001) -> 474.57803
M10: =M9^(1/(2024-2001)) -> 1.325389 | P10: =53*(1+0.2)^(2024-2001) -> 3511.1108
M11: =M10-1 -> 0.32538897 | P11: =53*(1+0.3)^(2024-2001) -> 22129.57
P12: =53*(1+0.4)^(2024-2001) -> 121680.42
P13: =53*(1+0.46)^(2024-2001) -> 319441.66

Sheet SQL
A1: SQL
A2: =CONCATENATE("(N","'",Sheet1!A2,"',",Sheet1!B2,",",Sheet1!C2,",",SQL!D2,Sheet1!D2,",",Sheet1!E2,",",Sheet1!F2,",",Sheet1!G2,",",Sheet1!H2,",",Sheet1!I2,",",Sheet1!J2,",",Sheet1!K2,",",Sheet1!M2,",",Sheet1!N2,",",Sheet1!O2,",",Sheet1!Q2,",",Sheet1!R2,",",Sheet1!S2,",N'",Sheet1!T2,"',","Null",",","Null",$B$2,"),") -> (N'ANTERO RESOURCES Corp',2013,6613581,3014921,3598660,1313134,971927,341207,-18930,-0.09,534707,-2673592,-2138885,2137383,63.15,-701.666666666667,-0.00286229200186707,N'NASDAQ',Null,Null ,CURRENT_TIMESTAMP, N'Mohan Hanumantha',CURRENT_TIMESTAMP, N'Mohan Hanumantha'), | B2: ,CURRENT_TIMESTAMP, N'Mohan Hanumantha',CURRENT_TIMESTAMP, N'Mohan Hanumantha'
A3: =CONCATENATE("(N","'",Sheet1!A3,"',",Sheet1!B3,",",Sheet1!C3,",",SQL!D3,Sheet1!D3,",",Sheet1!E3,",",Sheet1!F3,",",Sheet1!G3,",",Sheet1!H3,",",Sheet1!I3,",",Sheet1!J3,",",Sheet1!K3,",",Sheet1!M3,",",Sheet1!N3,",",Sheet1!O3,",",Sheet1!Q3,",",Sheet1!R3,",",Sheet1!S3,",N'",Sheet1!T3,"',","Null",",","Null",$B$2,"),") -> (N'ANTERO RESOURCES Corp',2014,11573495,6099665,5473830,2720632,1420898,1299734,673587,2.57,998121,-4089650,-3091529,3320021,40.6,15.7976653696498,0.0582008287038617,N'NASDAQ',Null,Null ,CURRENT_TIMESTAMP, N'Mohan Hanumantha',CURRENT_TIMESTAMP, N'Mohan Hanumantha'),
A4: =CONCATENATE("(N","'",Sheet1!A4,"',",Sheet1!B4,",",Sheet1!C4,",",SQL!D4,Sheet1!D4,",",Sheet1!E4,",",Sheet1!F4,",",Sheet1!G4,",",Sheet1!H4,",",Sheet1!I4,",",Sheet1!J4,",",Sheet1!K4,",",Sheet1!M4,",",Sheet1!N4,",",Sheet1!O4,",",Sheet1!Q4,",",Sheet1!R4,",",Sheet1!S4,",N'",Sheet1!T4,"',","Null",",","Null",$B$2,"),") -> (N'ANTERO RESOURCES Corp',2015,14155224,6868546,7286678,3954858,2164572,1790286,941364,3.43,1006381,-2298159,-1291778,1069272,21.75,6.34110787172012,0.0665029391269259,N'NASDAQ',Null,Null ,CURRENT_TIMESTAMP, N'Mohan Hanumantha',CURRENT_TIMESTAMP, N'Mohan Hanumantha'),
A5: =CONCATENATE("(N","'",Sheet1!A5,"',",Sheet1!B5,",",Sheet1!C5,",",SQL!D5,Sheet1!D5,",",Sheet1!E5,",",Sheet1!F5,",",Sheet1!G5,",",Sheet1!H5,",",Sheet1!I5,",",Sheet1!J5,",",Sheet1!K5,",",Sheet1!M5,",",Sheet1!N5,",",Sheet1!O5,",",Sheet1!Q5,",",Sheet1!R5,",",Sheet1!S5,",N'",Sheet1!T5,"',","Null",",","Null",$B$2,"),") -> (N'ANTERO RESOURCES Corp',2016,14255550,6526972,7728578,1744525,2720326,-975801,-848816,-2.88,1241256,-2395138,-1153882,1162019,23.89,-8.29513888888889,-0.0595428447166191,N'NASDAQ',Null,Null ,CURRENT_TIMESTAMP, N'Mohan Hanumantha',CURRENT_TIMESTAMP, N'Mohan Hanumantha'),
A6: =CONCATENATE("(N","'",Sheet1!A6,"',",Sheet1!B6,",",Sheet1!C6,",",SQL!D6,Sheet1!D6,",",Sheet1!E6,",",Sheet1!F6,",",Sheet1!G6,",",Sheet1!H6,",",Sheet1!I6,",",Sheet1!J6,",",Sheet1!K6,",",Sheet1!M6,",",Sheet1!N6,",",Sheet1!O6,",",Sheet1!Q6,",",Sheet1!R6,",",Sheet1!S6,",N'",Sheet1!T6,"',","Null",",","Null",$B$2,"),") -> (N'ANTERO RESOURCES Corp',2017,15261490,6385354,8876136,3655574,2915481,740093,615070,1.95,2006291,-2461630,-455339,452170,19.24,9.86666666666667,0.0403020937012048,N'NASDAQ',Null,Null ,CURRENT_TIMESTAMP, N'Mohan Hanumantha',CURRENT_TIMESTAMP, N'Mohan Hanumantha'),
A7: =CONCATENATE("(N","'",Sheet1!A7,"',",Sheet1!B7,",",Sheet1!C7,",",SQL!D7,Sheet1!D7,",",Sheet1!E7,",",Sheet1!F7,",",Sheet1!G7,",",Sheet1!H7,",",Sheet1!I7,",",Sheet1!J7,",",Sheet1!K7,",",Sheet1!M7,",",Sheet1!N7,",",Sheet1!O7,",",Sheet1!Q7,",",Sheet1!R7,",",Sheet1!S7,",N'",Sheet1!T7,"',","Null",",","Null",$B$2,"),") -> (N'ANTERO RESOURCES Corp',2018,15519464,7031987,8487477,4139626,4067721,71905,-397517,-1.26,2081987,-2350724,-268737,240296,9.2,-7.3015873015873,-0.0256140933733278,N'NASDAQ',Null,Null ,CURRENT_TIMESTAMP, N'Mohan Hanumantha',CURRENT_TIMESTAMP, N'Mohan Hanumantha'),
A8: =CONCATENATE("(N","'",Sheet1!A8,"',",Sheet1!B8,",",Sheet1!C8,",",SQL!D8,Sheet1!D8,",",Sheet1!E8,",",Sheet1!F8,",",Sheet1!G8,",",Sheet1!H8,",",Sheet1!I8,",",Sheet1!J8,",",Sheet1!K8,",",Sheet1!M8,",",Sheet1!N8,",",Sheet1!O8,",",Sheet1!Q8,",",Sheet1!R8,",",Sheet1!S8,",N'",Sheet1!T8,"',","Null",",","Null",$B$2,"),") -> (N'ANTERO RESOURCES Corp',2019,15197569,8226826,6970743,4408690,5395735,-987045,-340129,-1.11,1103458,-1041490,61968,557564,2.88,-2.59459459459459,-0.0223804873003044,N'NASDAQ',Null,Null ,CURRENT_TIMESTAMP, N'Mohan Hanumantha',CURRENT_TIMESTAMP, N'Mohan Hanumantha'),
A9: =CONCATENATE("(N","'",Sheet1!A9,"',",Sheet1!B9,",",Sheet1!C9,",",SQL!D9,Sheet1!D9,",",Sheet1!E9,",",Sheet1!F9,",",Sheet1!G9,",",Sheet1!H9,",",Sheet1!I9,",",Sheet1!J9,",",Sheet1!K9,",",Sheet1!M9,",",Sheet1!N9,",",Sheet1!O9,",",Sheet1!Q9,",",Sheet1!R9,",",Sheet1!S9,",N'",Sheet1!T9,"',","Null",",","Null",$B$2,"),") -> (N'ANTERO RESOURCES Corp',2020,13150845,7060574,6090271,3491699,4445146,-953447,-1267897,-4.65,735640,-530061,205579,-205579,5.57,-1.19784946236559,-0.0964118275289535,N'NASDAQ',Null,Null ,CURRENT_TIMESTAMP, N'Mohan Hanumantha',CURRENT_TIMESTAMP, N'Mohan Hanumantha'),
A10: =CONCATENATE("(N","'",Sheet1!A10,"',",Sheet1!B10,",",Sheet1!C10,",",SQL!D10,Sheet1!D10,",",Sheet1!E10,",",Sheet1!F10,",",Sheet1!G10,",",Sheet1!H10,",",Sheet1!I10,",",Sheet1!J10,",",Sheet1!K10,",",Sheet1!M10,",",Sheet1!N10,",",Sheet1!O10,",",Sheet1!Q10,",",Sheet1!R10,",",Sheet1!S10,",N'",Sheet1!T10,"',","Null",",","Null",$B$2,"),") -> (N'ANTERO RESOURCES Corp',2021,13896528,7830436,6066092,4619432,4595572,23860,-186899,-0.61,1660116,-710784,949332,-949332,17.33,-28.4098360655738,-0.0134493306529516,N'NASDAQ',Null,Null ,CURRENT_TIMESTAMP, N'Mohan Hanumantha',CURRENT_TIMESTAMP, N'Mohan Hanumantha'),
A11: =CONCATENATE("(N","'",Sheet1!A11,"',",Sheet1!B11,",",Sheet1!C11,",",SQL!D11,Sheet1!D11,",",Sheet1!E11,",",Sheet1!F11,",",Sheet1!G11,",",Sheet1!H11,",",Sheet1!I11,",",Sheet1!J11,",",Sheet1!K11,",",Sheet1!M11,",",Sheet1!N11,",",Sheet1!O11,",",Sheet1!Q11,",",Sheet1!R11,",",Sheet1!S11,",N'",Sheet1!T11,"',","Null",",","Null",$B$2,"),") -> (N'ANTERO RESOURCES Corp',2022,14118039,7100885,7017154,7138436,4564531,2573905,1898771,6.18,3051342,-943612,2107730,-2107730,29.95,4.8462783171521,0.134492545317377,N'NASDAQ',Null,Null ,CURRENT_TIMESTAMP, N'Mohan Hanumantha',CURRENT_TIMESTAMP, N'Mohan Hanumantha'),
A12: =CONCATENATE("(N","'",Sheet1!A12,"',",Sheet1!B12,",",Sheet1!C12,",",SQL!D12,Sheet1!D12,",",Sheet1!E12,",",Sheet1!F12,",",Sheet1!G12,",",Sheet1!H12,",",Sheet1!I12,",",Sheet1!J12,",",Sheet1!K12,",",Sheet1!M12,",",Sheet1!N12,",",Sheet1!O12,",",Sheet1!Q12,",",Sheet1!R12,",",Sheet1!S12,",N'",Sheet1!T12,"',","Null",",","Null",$B$2,"),") -> (N'Callon Petroleum',2012,378173,172202,205971,110733,100043,10690,2747,0.07,51290,-93703,-42413,-243,62.9,898.571428571428,0.00726387129699899,N'NASDAQ',Null,Null ,CURRENT_TIMESTAMP, N'Mohan Hanumantha',CURRENT_TIMESTAMP, N'Mohan Hanumantha'),
A13: =CONCATENATE("(N","'",Sheet1!A13,"',",Sheet1!B13,",",Sheet1!C13,",",SQL!D13,Sheet1!D13,",",Sheet1!E13,",",Sheet1!F13,",",Sheet1!G13,",",Sheet1!H13,",",Sheet1!I13,",",Sheet1!J13,",",Sheet1!K13,",",Sheet1!M13,",",Sheet1!N13,",",Sheet1!O13,",",Sheet1!Q13,",",Sheet1!R13,",",Sheet1!S13,",N'",Sheet1!T13,"',","Null",",","Null",$B$2,"),") -> (N'Callon Petroleum',2013,423953,144859,279094,102569,91905,10664,-323,-0.01,54329,-79804,-25475,27348,37,-3700,-0.000761876906166485,N'NASDAQ',Null,Null ,CURRENT_TIMESTAMP, N'Mohan Hanumantha',CURRENT_TIMESTAMP, N'Mohan Hanumantha'),
A14: =CONCATENATE("(N","'",Sheet1!A14,"',",Sheet1!B14,",",Sheet1!C14,",",SQL!D14,Sheet1!D14,",",Sheet1!E14,",",Sheet1!F14,",",Sheet1!G14,",",Sheet1!H14,",",Sheet1!I14,",",Sheet1!J14,",",Sheet1!K14,",",Sheet1!M14,",",Sheet1!N14,",",Sheet1!O14,",",Sheet1!Q14,",",Sheet1!R14,",",Sheet1!S14,",N'",Sheet1!T14,"',","Null",",","Null",$B$2,"),") -> (N'Callon Petroleum',2014,876770,443035,433735,151862,113592,38270,29871,0.67,94387,-452501,-358114,356070,83.7,124.925373134328,0.0340693682493698,N'NASDAQ',Null,Null ,CURRENT_TIMESTAMP, N'Mohan Hanumantha',CURRENT_TIMESTAMP, N'Mohan Hanumantha'),
... A209: =CONCATENATE("(N","'",Sheet1!A209,"',",Sheet1!B209,",",Sheet1!C209,",",SQL!D209,Sheet1!D209,",",Sheet1!E209,",",Sheet1!F209,",",Sheet1!G209,",",Sheet1!H209,",",Sheet1!I209,",",Sheet1!J209,",",Sheet1!K209,",",Sheet1!M209,",",Sheet1!N209,",",Sheet1!O209,",",Sheet1!Q209,",",Sheet1!R209,",",Sheet1!S209,",N'",Sheet1!T209,"',","Null",",","Null",$B$2,"),") -> (N'Vital Energy',2022,2726114,1615368,1110746,1920796,860634,1060162,631512,37.88,829620,-475952,353668,-366031,79,2.08553326293559,0.231652821562121,N'NASDAQ',Null,Null ,CURRENT_TIMESTAMP, N'Mohan Hanumantha',CURRENT_TIMESTAMP, N'Mohan Hanumantha'),

Sheet Sheet2
A15: Chesapeake Energy | B15: 2015 | C15: 2 | D15: pdf
A16: Chesapeake Energy | B16: 2016 | C16: 2 | D16: pdf
A17: Chesapeake Energy | B17: 2017 | C17: 2 | D17: pdf
A18: Chesapeake Energy | B18: 2018 | C18: 2 | D18: pdf
A19: Chesapeake Energy | B19: 2019 | C19: 2 | D19: pdf | E19: https://app.quotemedia.com/data/downloadFiling?webmasterId=101533&ref=114829726&type=PDF&symbol=CHK&companyName=Chesapeake+Energy+Corporation&formType=10-K&dateFiled=2020-02-27&CK=895126
A20: Chesapeake Energy | B20: 2020 | C20: 2 | D20: pdf | E20: https://app.quotemedia.com/data/downloadFiling?webmasterId=101533&ref=115684457&type=PDF&symbol=CHK&companyName=Chesapeake+Energy+Corporation&formType=10-K&dateFiled=2021-03-01&CK=895126
A21: Chesapeake Energy | B21: 2021 | C21: 2 | D21: pdf | E21: https://app.quotemedia.com/data/downloadFiling?webmasterId=101533&ref=116490942&type=PDF&symbol=CHK&companyName=Chesapeake+Energy+Corporation&formType=10-K&dateFiled=2022-02-24&CK=895126
A22: Chesapeake Energy | B22: 2022 | C22: 2 | D22: pdf | E22: https://app.quotemedia.com/data/downloadFiling?webmasterId=101533&ref=117270814&type=PDF&symbol=CHK&companyName=Chesapeake+Energy+Corporation&formType=10-K&dateFiled=2023-02-22&CK=895126
A23: Chord Energy | B23: 2022 | C23: 2 | D23: pdf | E23: https://app.quotemedia.com/data/downloadFiling?webmasterId=101533&ref=117294757&type=PDF&symbol=CHRD&companyName=Chord+Energy+Corporation&formType=10-K&dateFiled=2023-02-28&CK=1486159
A24: Civitas Resources | B24: 2021 | C24: 2 | D24: pdf | E24: https://d18rn0p25nwr6d.cloudfront.net/CIK-0001509589/4d17e6a3-90f7-4278-b108-816836fea1da.pdf
A25: Civitas Resources | B25: 2022 | C25: 2 | D25: pdf | E25: https://d18rn0p25nwr6d.cloudfront.net/CIK-0001509589/5096b438-430b-4152-97bf-72aada14563c.pdf
A26: ConocoPhillips | B26: 2012 | C26: 2 | D26: webpage | E26: https://www.sec.gov/Archives/edgar/data/0001163165/000119312513065426/d452384d10k.htm
A27: ConocoPhillips | B27: 2013 | C27: 2 | D27: webpage | E27: https://www.sec.gov/Archives/edgar/data/0001163165/000119312514066358/d665238d10k.htm
A28: ConocoPhillips | B28: 2014 | C28: 2 | D28: webpage | E28: https://www.sec.gov/Archives/edgar/data/0001163165/000119312515059281/d869001d10k.htm
A29: ConocoPhillips | B29: 2015 | C29: 2 | D29: webpage | E29: https://www.sec.gov/Archives/edgar/data/0001163165/000119312516472901/d145414d10k.htm
A30: ConocoPhillips | B30: 2016 | C30: 2 | D30: webpage | E30: https://www.sec.gov/Archives/edgar/data/0001163165/000119312517050077/d264316d10k.htm
... A209: XTO Energy, Inc. | B209: 2022 | C209: 2 | D209: webpage | E209: https://ir.exxonmobil.com/static-files/7ac1ca73-14ce-4c13-b34d-267d59a2565f
